metanetwork/__init__.py
metanetwork/_arbitratednetwork.py
metanetwork/_ensemble.py
metanetwork/_metanetwork.py
metanetwork/_nn.py
metanetwork/analysis/__init__.py
metanetwork/analysis/_confusion_matrix.py
metanetwork/analysis/_report.py
metanetwork/analysis/metrics.py
metanetwork/ml/__init__.py
metanetwork/ml/activation.py
metanetwork/ml/loss.py
metanetwork/ml/optimizer.py
metanetwork/ml/regularizer.py
metanetwork/utils/__init__.py
metanetwork/utils/_base.py
metanetwork/utils/_batch_dataset.py
metanetwork/utils/_check.py
metanetwork/utils/_estimator.py
metanetwork/utils/_misc.py
tests/__init__.py
tests/test_an.py
tests/test_fixtures.py
tests/test_mn.py
tests/test_nn.py
tests/test_scaffold.py
metanetwork-0.1.0.dist-info/LICENSE
metanetwork-0.1.0.dist-info/METADATA
metanetwork-0.1.0.dist-info/WHEEL
metanetwork-0.1.0.dist-info/top_level.txt
metanetwork-0.1.0.dist-info/zip-safe
metanetwork-0.1.0.dist-info/RECORD
