Metadata-Version: 2.1
Name: metanetwork
Version: 0.1.0
Summary: Structured Ensemble Learning
Home-page: http://github.com/paradoxysm/metanetwork
Author: paradoxysm
Author-email: paradoxysm.dev@gmail.com
License: BSD-3-Clause
Download-URL: https://github.com/paradoxysm/metanetwork/archive/0.1.0.tar.gz
Keywords: python,ml,ensemble,neural-network
Platform: UNKNOWN
Classifier: Development Status :: 4 - Beta
Classifier: Intended Audience :: Developers
Classifier: Natural Language :: English
Classifier: License :: OSI Approved :: BSD License
Classifier: Operating System :: OS Independent
Classifier: Programming Language :: Python
Classifier: Programming Language :: Python :: 3
Classifier: Programming Language :: Python :: 3.4
Classifier: Programming Language :: Python :: 3.5
Classifier: Programming Language :: Python :: 3.6
Classifier: Programming Language :: Python :: 3.7
Classifier: Topic :: Software Development :: Libraries :: Python Modules
Classifier: Topic :: Scientific/Engineering :: Artificial Intelligence
Classifier: Topic :: Scientific/Engineering :: Information Analysis
Classifier: Intended Audience :: Science/Research
Requires-Python: >=3.4, <4
Requires-Dist: numpy
Requires-Dist: tqdm
Requires-Dist: sklearn
